{
    "value": {
        "seenScripts": [
            [
                "/root/iris/build.sc",
                "import mill._, scalalib._\n\nobject Iris extends RootModule with ScalaModule {\n  def scalaVersion = \"3.3.1\"\n\n  // Here you add the external libraries (dependencies) that you want to use. They are of the form \"author::name:version\"\n  def ivyDeps = Agg(\n    ivy\"com.lihaoyi::os-lib:0.9.1\",\n  )\n\n  // Choose a main class to use for `mill run` if there are multiple present\n  def mainClass = Some(\"iris.main\")\n  val src = os.pwd / \"src\"\n\n  // os.pwd refers to where this file is located\n  // Add (or replace) source folders for the module to use\n  def sources = T.sources(src)\n\n  object IrisSetup extends ScalaModule {\n    def scalaVersion = \"3.3.1\"\n\n    // Choose a main class to use for `mill run` if there are multiple present\n    def mainClass = Some(\"iris-setup.main\")\n    // os.pwd refers to where this file is located\n\n    // Add (or replace) source folders for the module to use\n    def sources = T.sources(\n       src / \"iris-setup\",\n    )\n  }\n}\n\n"
            ]
        ],
        "repos": [],
        "ivyDeps": [],
        "importGraphEdges": [
            [
                "/root/iris/build.sc",
                []
            ]
        ],
        "errors": [],
        "millImport": false
    },
    "valueHash": 90974995,
    "inputsHash": -517448797
}